huaweicloudsdkpangulargemodels/__init__.py
huaweicloudsdkpangulargemodels/v1/__init__.py
huaweicloudsdkpangulargemodels/v1/pangulargemodels_async_client.py
huaweicloudsdkpangulargemodels/v1/pangulargemodels_client.py
huaweicloudsdkpangulargemodels/v1/model/__init__.py
huaweicloudsdkpangulargemodels/v1/model/chat_choice.py
huaweicloudsdkpangulargemodels/v1/model/chat_completion_req.py
huaweicloudsdkpangulargemodels/v1/model/completion_usage.py
huaweicloudsdkpangulargemodels/v1/model/execute_chat_completion_request.py
huaweicloudsdkpangulargemodels/v1/model/execute_chat_completion_response.py
huaweicloudsdkpangulargemodels/v1/model/execute_text_completion_request.py
huaweicloudsdkpangulargemodels/v1/model/execute_text_completion_response.py
huaweicloudsdkpangulargemodels/v1/model/message.py
huaweicloudsdkpangulargemodels/v1/model/message_item.py
huaweicloudsdkpangulargemodels/v1/model/text_choice.py
huaweicloudsdkpangulargemodels/v1/model/text_completion_req.py
huaweicloudsdkpangulargemodels/v1/region/__init__.py
huaweicloudsdkpangulargemodels/v1/region/pangulargemodels_region.py
huaweicloudsdkpangulargemodels/v2/__init__.py
huaweicloudsdkpangulargemodels/v2/pangulargemodels_async_client.py
huaweicloudsdkpangulargemodels/v2/pangulargemodels_client.py
huaweicloudsdkpangulargemodels/v2/model/__init__.py
huaweicloudsdkpangulargemodels/v2/model/chat_choice.py
huaweicloudsdkpangulargemodels/v2/model/chat_completion_req.py
huaweicloudsdkpangulargemodels/v2/model/completion_usage.py
huaweicloudsdkpangulargemodels/v2/model/execute_chat_completion_request.py
huaweicloudsdkpangulargemodels/v2/model/execute_chat_completion_response.py
huaweicloudsdkpangulargemodels/v2/model/execute_text_completion_request.py
huaweicloudsdkpangulargemodels/v2/model/execute_text_completion_response.py
huaweicloudsdkpangulargemodels/v2/model/message.py
huaweicloudsdkpangulargemodels/v2/model/message_item.py
huaweicloudsdkpangulargemodels/v2/model/text_choice.py
huaweicloudsdkpangulargemodels-3.1.184.dist-info/METADATA
huaweicloudsdkpangulargemodels-3.1.184.dist-info/WHEEL
huaweicloudsdkpangulargemodels-3.1.184.dist-info/licenses/LICENSE
huaweicloudsdkpangulargemodels-3.1.184.dist-info/RECORD
